gx_converter/__init__.py
gx_converter/g_code_property_extractor.py
gx_converter/g_code_transformer.py
gx_converter/header.py
gx_converter/main.py
gx_converter/thumbnail.bmp
gx_converter/tests/__init__.py
gx_converter/tests/test_g_code_property_extractor.py
gx_converter/tests/test_g_code_transformer.py
gx_converter-0.2.0.dist-info/licenses/LICENSE
gx_converter-0.2.0.dist-info/METADATA
gx_converter-0.2.0.dist-info/WHEEL
gx_converter-0.2.0.dist-info/entry_points.txt
gx_converter-0.2.0.dist-info/top_level.txt
gx_converter-0.2.0.dist-info/RECORD
